[
  {
    "name": "Josiah Lucas",
    "email": "facilisis.suspendisse.commodo@google.couk",
    "id": 1,
    "address": "1064 Amet, Av.",
    "phone": "1-641-616-7104"
  },
  {
    "name": "Gregory Moreno",
    "email": "pellentesque.tellus.sem@aol.edu",
    "id": 2,
    "address": "690-2203 Interdum Av.",
    "phone": "1-801-579-0333"
  },
  {
    "name": "McKenzie Price",
    "email": "et.euismod@aol.couk",
    "id": 3,
    "address": "Ap #404-8325 Ac Ave",
    "phone": "1-675-836-1393"
  },
  {
    "name": "Ivan Myers",
    "email": "amet.dapibus@outlook.org",
    "id": 4,
    "address": "Ap #173-326 Vulputate Street",
    "phone": "1-787-442-6528"
  },
  {
    "name": "Jordan Monroe",
    "email": "sapien.aenean@hotmail.edu",
    "id": 5,
    "address": "P.O. Box 146, 7992 Nisl. Street",
    "phone": "(817) 361-7094"
  },
  {
    "name": "Yasir Dyer",
    "email": "in@hotmail.org",
    "id": 6,
    "address": "1691 Dignissim Road",
    "phone": "1-302-328-5628"
  },
  {
    "name": "Upton Garcia",
    "email": "elementum.purus@hotmail.edu",
    "id": 7,
    "address": "P.O. Box 918, 2239 Mauris, Rd.",
    "phone": "(750) 398-4028"
  },
  {
    "name": "Craig Mayer",
    "email": "sed.tortor@hotmail.ca",
    "id": 8,
    "address": "Ap #185-2114 Hendrerit. Av.",
    "phone": "(574) 618-2730"
  },
  {
    "name": "Giacomo Cameron",
    "email": "aliquam.erat@outlook.edu",
    "id": 9,
    "address": "Ap #183-260 Dictum Avenue",
    "phone": "(473) 712-6311"
  },
  {
    "name": "Wing Beard",
    "email": "tempor.bibendum.donec@google.com",
    "id": 10,
    "address": "Ap #572-1574 Ac St.",
    "phone": "(857) 153-3516"
  },
  {
    "name": "Rhona Roach",
    "email": "lectus.a.sollicitudin@aol.org",
    "id": 11,
    "address": "P.O. Box 163, 279 Pede St.",
    "phone": "(446) 467-4101"
  },
  {
    "name": "Amery Rivas",
    "email": "ligula.aenean@outlook.edu",
    "id": 12,
    "address": "Ap #484-1516 Cras St.",
    "phone": "(633) 224-4098"
  },
  {
    "name": "Amy Edwards",
    "email": "nec.mauris@outlook.ca",
    "id": 13,
    "address": "4622 Elit Ave",
    "phone": "(815) 225-8559"
  },
  {
    "name": "Rafael Kent",
    "email": "nulla.at.sem@yahoo.org",
    "id": 14,
    "address": "Ap #274-1468 Sed St.",
    "phone": "(585) 474-8444"
  },
  {
    "name": "Claire Mclaughlin",
    "email": "euismod@yahoo.edu",
    "id": 15,
    "address": "198-8005 Vestibulum, Rd.",
    "phone": "(635) 894-4325"
  },
  {
    "name": "Alan Hodges",
    "email": "purus.nullam@yahoo.com",
    "id": 16,
    "address": "Ap #808-8316 Donec Road",
    "phone": "(146) 274-3382"
  },
  {
    "name": "Eaton Tanner",
    "email": "quam.dignissim@aol.org",
    "id": 17,
    "address": "527-3933 Eget Ave",
    "phone": "1-726-887-8220"
  },
  {
    "name": "Lars Moses",
    "email": "at.libero.morbi@outlook.org",
    "id": 18,
    "address": "P.O. Box 392, 3463 Nec Road",
    "phone": "1-709-705-3540"
  },
  {
    "name": "Isaac Burke",
    "email": "eget.laoreet.posuere@hotmail.net",
    "id": 19,
    "address": "7051 Faucibus. Street",
    "phone": "(257) 682-8571"
  },
  {
    "name": "Slade Davidson",
    "email": "imperdiet@aol.com",
    "id": 20,
    "address": "P.O. Box 754, 4436 Iaculis St.",
    "phone": "1-934-237-7653"
  }
]
